surfcut/__init__.py
surfcut/cli.py
surfcut/gui.py
surfcut/run.py
surfcut/straight.py
surfcut/viewer/__init__.py
surfcut/viewer/viewer.py
surfcut-0.0.3.dist-info/METADATA
surfcut-0.0.3.dist-info/WHEEL
surfcut-0.0.3.dist-info/entry_points.txt
surfcut-0.0.3.dist-info/top_level.txt
surfcut-0.0.3.dist-info/RECORD
