Metadata-Version: 2.1
Name: surfcut
Version: 0.0.3
Summary: Cutting confocal stacks at various depths relative to surface signal 
Home-page: UNKNOWN
License: UNKNOWN
Platform: UNKNOWN
Requires-Python: >=3.6
Requires-Dist: numpy
Requires-Dist: scipy
Requires-Dist: napari (>=0.2.12)
Requires-Dist: tifffile
Requires-Dist: pillow
Requires-Dist: scikit-image
